speech2tima/__init__.py
speech2tima/recognizer.py
speech2tima-0.0.5.dist-info/METADATA
speech2tima-0.0.5.dist-info/WHEEL
speech2tima-0.0.5.dist-info/entry_points.txt
speech2tima-0.0.5.dist-info/top_level.txt
speech2tima-0.0.5.dist-info/RECORD
