Metadata-Version: 2.1
Name: speech2tima
Version: 0.0.5
Summary: A package for speech recognition using SpeechRecognition library. Main function is gettext
Home-page: https://github.com/titas2003/speech2tima.git
Author: Titas Majumder
Author-email: titas20031996@gmail.com
License: MIT
Platform: UNKNOWN
Requires-Dist: SpeechRecognition
Requires-Dist: pyaudio
